LeanEuler/__init__.py
LeanEuler/lean_euler.py
LeanEuler/lean_euler_helper_funcs.py
LeanEuler/ASPEncodings/__init__.py
LeanEuler/ASPEncodings/mnpw_encoding.py
LeanEuler/ASPEncodings/rcc_encoding.py
LeanEuler/CleanTaxParser/CleanTaxLexer.py
LeanEuler/CleanTaxParser/CleanTaxListener.py
LeanEuler/CleanTaxParser/CleanTaxParser.py
LeanEuler/CleanTaxParser/__init__.py
LeanEuler/CleanTaxParser/parse_cleantax.py
LeanEuler/Visualizations/__init__.py
LeanEuler/Visualizations/euler_input_visualization_nxpd.py
LeanEuler/Visualizations/euler_output_visualization_nxpd.py
LeanEuler/Visualizations/euler_output_visualization_old.py
LeanEuler-0.0.4.data/scripts/le_cleantax_to_asp
LeanEuler-0.0.4.data/scripts/le_cleantax_to_db
LeanEuler-0.0.4.data/scripts/le_db_to_asp
LeanEuler-0.0.4.dist-info/LICENSE
LeanEuler-0.0.4.dist-info/METADATA
LeanEuler-0.0.4.dist-info/WHEEL
LeanEuler-0.0.4.dist-info/top_level.txt
LeanEuler-0.0.4.dist-info/RECORD
