Metadata-Version: 2.1
Name: LeanEuler
Version: 0.0.4
Summary: Lean implementation of core of EulerX functionality
Home-page: https://github.com/idaks/LeanEuler
Author: Sahil Gupta
Author-email: 
License: UNKNOWN
Platform: UNKNOWN
Classifier: Programming Language :: Python :: 3
Classifier: License :: OSI Approved :: Apache Software License
Classifier: Operating System :: OS Independent
Requires-Dist: pw-explorer (>=0.0.23)
Requires-Dist: antlr4-python3-runtime (>=4.7.2)
Requires-Dist: anytree (>=2.6.0)
Requires-Dist: argparse (>=1.4.0)
Requires-Dist: networkx (>=2.2)
Requires-Dist: nxpd (>=0.2.0)
Requires-Dist: pandas (>=0.24.1)
Requires-Dist: numpy (>=1.16.2)
Requires-Dist: matplotlib (>=3.0.3)
Requires-Dist: scipy (>=1.2.1)
